Workbook

Sheet LIBRO DIARIO
A1: LIBRO DIARIO
A3: Cálculo Auxiliar en Esquema T | F3: FORMATO DEL LIBRO DIARIO
A4: DEBE | C4: HABER | F4: NRO | G4: FECHA | H4: CUENTAS CONTABLES | I4: DEBE | J4: HABER
F5: 1 | G5: 46143 | H5: CAJA | I5: 100000000
H6: CAPITAL | J6: 100000000
H7: ASIENTO DE APERTURA DE LA EMPRESA
H8: WW - UNIPERSONAL
F10: 2 | G10: 46144 | H10: BANCO X CTA CTE | I10: 95000000
H11: CAJA | J11: 95000000
H12: DEPOSITO EN CTA CTE SEGÚN BOLETA
F14: 3 | G14: 46145 | H14: IMPUESTOS, TASAS Y PATENTES | I14: 600000
H15: BANCO X CTA CTE | J15: 600000
H16: PAGO DE PATENTE COMERCIAL SEGÚN
H17: COMPROBANTE DE INGRESO
F19: 4 | G19: 46146 | H19: MERCADERIAS | I19: 30000000
H20: IVA CF 10% | I20: 3000000
H21: BANCO X CTA CTE | J21: 20000000
H22: PROVEEDORES | J22: 13000000
H23: COMPRA DE 3 GENERADORES A GS.11.000.000 C/U SEGÚN F.CREDITO.
F25: 5 | G25: 46147 | H25: MUEBLES Y EQUIPOS | I25: 1200000
H26: IVA CF 10% | I26: 120000
H27: ACREEDORES VARIOS | J27: 1320000
H28: COMPRA DE MOBILIARIOS PARA USO EN EL LOCAL
F30: 6 | G30: 46148 | H30: EQUIPOS DE INFORMATICA | I30: 1000000
H31: IVA CF 10% | I31: 100000
H32: BANCO X CTA CTE | J32: 1100000
H33: COMPRA DE COMPUTADORA PARA USO DE LA EMPRESA SEGÚN FACTURA CONTADO
F35: 7 | G35: 46160 | H35: BANCO X CTA CTE | I35: 44000000
H36: VENTA DE MERCADERIAS | J36: 40000000 | K36: #Error | L36: #debe de ser 44.000.000
H37: IVA DF 10% | J37: 4000000 | L37: #se modificara para que se pueda proseguir
H38: VENTA DE 2 GENERADORES A GS. 20.000.000 C/U SEGÚN FACTURA
F40: 8 | G40: 46160 | H40: COSTO DE MERCADERIAS | I40: 20000000
H41: MERCADERIAS | J41: 20000000
H42: COSTEO SEGÚN INFORME DEPOSITO
F44: 9 | G44: 46173 | H44: SUELDOS Y JORNALES | I44: 5000000
H45: APORTE PATRONAL | I45: 825000
H46: IPS A PAGAR | J46: 1275000
H47: BANCO X CTA CTE | J47: 4550000
H48: PAGO DE SALARIO AL PERSONAL
F50: 10 | G50: 46173 | H50: HONORARIOS PROFESIONALES | I50: 6000000
H51: IVA CF 10% | I51: 600000
H52: HONORARIOS A PAGAR | J52: 6600000
H53: PAGO DE HONROARIOS AL ABOGADO DE LA EMPRESA SEGÚN FACTURA
F55: 11 | G55: 46173 | H55: PROVEEDORES | I55: 3000000
H56: BANCO X CTA CTE | J56: 3000000
H57: PAGO PARCIAL POR LA DEUDA DE MERCADERIAS COMPRADAS EL 04/05
I59: =SUM(I5:I57) -> 310445000 | J59: =SUM(J5:J57) -> 310445000

Sheet LIBRO MAYOR
A1: FORMATO DEL LIBRO MAYOR
A3: FOLIO: | B3: 1 | C3: CUENTA: | D3: CAJA
A4: NRO | B4: FECHA | C4: DESCRIPCIÓN | D4: DEBE | E4: HABER | F4: SALDO
A5: 1 | B5: ='LIBRO DIARIO'!G5 -> 46143 | C5: ='LIBRO DIARIO'!H7 -> ASIENTO DE APERTURA DE LA EMPRESA | D5: ='LIBRO DIARIO'!I5 -> 100000000 | F5: =D5 -> 100000000
A6: 2 | B6: ='LIBRO DIARIO'!G10 -> 46144 | C6: ='LIBRO DIARIO'!H12 -> DEPOSITO EN CTA CTE SEGÚN BOLETA | E6: ='LIBRO DIARIO'!J11 -> 95000000 | F6: =F5-E6 -> 5000000
D7: =SUM(D5:D6) -> 100000000 | E7: =SUM(E6) -> 95000000
A11: FOLIO: | B11: 2 | C11: CUENTA: | D11: CAPITAL
A12: NRO | B12: FECHA | C12: DESCRIPCIÓN | D12: DEBE | E12: HABER | F12: SALDO
A13: 1 | B13: =B5 -> 46143 | C13: ='LIBRO DIARIO'!H7 -> ASIENTO DE APERTURA DE LA EMPRESA | E13: ='LIBRO DIARIO'!J6 -> 100000000 | F13: =E13 -> 100000000
E16: =E13 -> 100000000 | F16: =F13 -> 100000000
A19: FOLIO: | B19: 3 | C19: CUENTA: | D19: ='LIBRO DIARIO'!H10 -> BANCO X CTA CTE
A20: NRO | B20: FECHA | C20: DESCRIPCIÓN | D20: DEBE | E20: HABER | F20: SALDO
A21: ='LIBRO DIARIO'!F10 -> 2 | B21: ='LIBRO DIARIO'!G10 -> 46144 | C21: ='LIBRO DIARIO'!H12 -> DEPOSITO EN CTA CTE SEGÚN BOLETA | D21: ='LIBRO DIARIO'!I10 -> 95000000 | F21: =D21 -> 95000000
A22: 3 | B22: ='LIBRO DIARIO'!G14 -> 46145 | C22: ='LIBRO DIARIO'!H16 -> PAGO DE PATENTE COMERCIAL SEGÚN | E22: ='LIBRO DIARIO'!J15 -> 600000 | F22: =F21-E22 -> 94400000
A23: 4 | B23: ='LIBRO DIARIO'!G19 -> 46146 | C23: ='LIBRO DIARIO'!H23 -> COMPRA DE 3 GENERADORES A GS.11.000.000 C/U SEGÚN F.CREDITO. | E23: ='LIBRO DIARIO'!J21 -> 20000000 | F23: =F22-E23 -> 74400000
A24: 6 | B24: 46148 | C24: ='LIBRO DIARIO'!H33 -> COMPRA DE COMPUTADORA PARA USO DE LA EMPRESA SEGÚN FACTURA CONTADO | E24: ='LIBRO DIARIO'!J32 -> 1100000 | F24: =F23-E24 -> 73300000
A25: 7 | B25: ='LIBRO DIARIO'!G35 -> 46160 | C25: ='LIBRO DIARIO'!H38 -> VENTA DE 2 GENERADORES A GS. 20.000.000 C/U SEGÚN FACTURA | D25: ='LIBRO DIARIO'!I35 -> 44000000 | F25: =F24+D25 -> 117300000
A26: 9 | B26: ='LIBRO DIARIO'!G44 -> 46173 | C26: ='LIBRO DIARIO'!H48 -> PAGO DE SALARIO AL PERSONAL | E26: ='LIBRO DIARIO'!J47 -> 4550000 | F26: =F25-E26 -> 112750000
A27: 11 | B27: ='LIBRO DIARIO'!G55 -> 46173 | C27: ='LIBRO DIARIO'!H57 -> PAGO PARCIAL POR LA DEUDA DE MERCADERIAS COMPRADAS EL 04/05 | E27: ='LIBRO DIARIO'!J56 -> 3000000 | F27: =F26-E27 -> 109750000
D28: =SUM(D21:D27) -> 139000000 | E28: =SUM(E21:E27) -> 29250000
A30: FOLIO: | B30: 4 | C30: CUENTA: | D30: ='LIBRO DIARIO'!H14 -> IMPUESTOS, TASAS Y PATENTES
A31: NRO | B31: FECHA | C31: DESCRIPCIÓN | D31: DEBE | E31: HABER | F31: SALDO
A32: ='LIBRO DIARIO'!F14 -> 3 | B32: ='LIBRO DIARIO'!G14 -> 46145 | C32: ='LIBRO DIARIO'!H16 -> PAGO DE PATENTE COMERCIAL SEGÚN | D32: ='LIBRO DIARIO'!I14 -> 600000 | F32: =D32 -> 600000
D35: =D32 -> 600000 | F35: =F32 -> 600000
A38: FOLIO: | B38: 5 | C38: CUENTA: | D38: ='LIBRO DIARIO'!H19 -> MERCADERIAS
A39: NRO | B39: FECHA | C39: DESCRIPCIÓN | D39: DEBE | E39: HABER | F39: SALDO
A40: 4 | B40: ='LIBRO DIARIO'!G19 -> 46146 | C40: ='LIBRO DIARIO'!H23 -> COMPRA DE 3 GENERADORES A GS.11.000.000 C/U SEGÚN F.CREDITO. | D40: ='LIBRO DIARIO'!I19 -> 30000000 | F40: =D40 -> 30000000
A41: ='LIBRO DIARIO'!F40 -> 8 | B41: ='LIBRO DIARIO'!G40 -> 46160 | C41: ='LIBRO DIARIO'!H42 -> COSTEO SEGÚN INFORME DEPOSITO | E41: ='LIBRO DIARIO'!J41 -> 20000000 | F41: =F40-E41 -> 10000000
F43: =F41 -> 10000000
D44: =D40 -> 30000000 | E44: =E41 -> 20000000
A46: FOLIO: | B46: 6 | C46: CUENTA: | D46: ='LIBRO DIARIO'!H20 -> IVA CF 10%
A47: NRO | B47: FECHA | C47: DESCRIPCIÓN | D47: DEBE | E47: HABER | F47: SALDO
A48: =A40 -> 4 | B48: =B40 -> 46146 | C48: ='LIBRO DIARIO'!H23 -> COMPRA DE 3 GENERADORES A GS.11.000.000 C/U SEGÚN F.CREDITO. | D48: ='LIBRO DIARIO'!I20 -> 3000000 | F48: =D48 -> 3000000
A49: 5 | B49: 46147 | C49: ='LIBRO DIARIO'!H28 -> COMPRA DE MOBILIARIOS PARA USO EN EL LOCAL | D49: ='LIBRO DIARIO'!I26 -> 120000 | F49: =F48+D49 -> 3120000
A50: 10 | B50: ='LIBRO DIARIO'!G50 -> 46173 | C50: ='LIBRO DIARIO'!H53 -> PAGO DE HONROARIOS AL ABOGADO DE LA EMPRESA SEGÚN FACTURA | D50: ='LIBRO DIARIO'!I51 -> 600000 | F50: =F49+D50 -> 3720000
A51: 6 | B51: 46148 | C51: ='LIBRO DIARIO'!H33 -> COMPRA DE COMPUTADORA PARA USO DE LA EMPRESA SEGÚN FACTURA CONTADO | D51: 100000 | E51: 0 | F51: =F50+D51 -> 3820000
D52: =SUM(D48:D51) -> 3820000
A54: FOLIO: | B54: 7 | C54: CUENTA: | D54: PROVEEDORES
A55: NRO | B55: FECHA | C55: DESCRIPCIÓN | D55: DEBE | E55: HABER | F55: SALDO
A56: 4 | B56: =B48 -> 46146 | C56: ='LIBRO DIARIO'!H23 -> COMPRA DE 3 GENERADORES A GS.11.000.000 C/U SEGÚN F.CREDITO. | E56: ='LIBRO DIARIO'!J22 -> 13000000 | F56: =E56 -> 13000000
A57: ='LIBRO DIARIO'!F55 -> 11 | B57: ='LIBRO DIARIO'!G55 -> 46173 | C57: ='LIBRO DIARIO'!H57 -> PAGO PARCIAL POR LA DEUDA DE MERCADERIAS COMPRADAS EL 04/05 | D57: ='LIBRO DIARIO'!I55 -> 3000000 | F57: =F56+D57 -> 16000000
D59: =D57 -> 3000000 | E59: =E56 -> 13000000
A62: FOLIO: | B62: 8 | C62: CUENTA: | D62: MUEBLES Y EQUIPOS
A63: NRO | B63: FECHA | C63: DESCRIPCIÓN | D63: DEBE | E63: HABER | F63: SALDO
A64: 5 | B64: ='LIBRO DIARIO'!G25 -> 46147 | C64: ='LIBRO DIARIO'!H28 -> COMPRA DE MOBILIARIOS PARA USO EN EL LOCAL | D64: ='LIBRO DIARIO'!I25 -> 1200000 | F64: =D64 -> 1200000
D67: =D64 -> 1200000 | F67: =F64 -> 1200000
A70: FOLIO: | B70: 9 | C70: CUENTA: | D70: ACREEDORES VARIOS
A71: NRO | B71: FECHA | C71: DESCRIPCIÓN | D71: DEBE | E71: HABER | F71: SALDO
A72: 5 | B72: ='LIBRO DIARIO'!G25 -> 46147 | C72: ='LIBRO DIARIO'!H28 -> COMPRA DE MOBILIARIOS PARA USO EN EL LOCAL | E72: ='LIBRO DIARIO'!J27 -> 1320000 | F72: =E72 -> 1320000
D75: 0 | E75: =E72 -> 1320000 | F75: =E75 -> 1320000
A78: FOLIO: | B78: 10 | C78: CUENTA: | D78: ='LIBRO DIARIO'!H30 -> EQUIPOS DE INFORMATICA
A79: NRO | B79: FECHA | C79: DESCRIPCIÓN | D79: DEBE | E79: HABER | F79: SALDO
A80: 6 | B80: ='LIBRO DIARIO'!G30 -> 46148 | C80: ='LIBRO DIARIO'!H33 -> COMPRA DE COMPUTADORA PARA USO DE LA EMPRESA SEGÚN FACTURA CONTADO | D80: ='LIBRO DIARIO'!I30 -> 1000000 | F80: =D80 -> 1000000
D83: =D80 -> 1000000 | F83: =F80 -> 1000000
A86: FOLIO: | B86: 11 | C86: CUENTA: | D86: VENTA DE MERCADERIAS
A87: NRO | B87: FECHA | C87: DESCRIPCIÓN | D87: DEBE | E87: HABER | F87: SALDO
A88: 7 | B88: ='LIBRO DIARIO'!G35 -> 46160 | C88: ='LIBRO DIARIO'!H38 -> VENTA DE 2 GENERADORES A GS. 20.000.000 C/U SEGÚN FACTURA | E88: ='LIBRO DIARIO'!J36 -> 40000000 | F88: =E88 -> 40000000
D91: 0 | E91: =F91 -> 40000000 | F91: =F88 -> 40000000
A94: FOLIO: | B94: 12 | C94: CUENTA: | D94: IVA DF 10%
A95: NRO | B95: FECHA | C95: DESCRIPCIÓN | D95: DEBE | E95: HABER | F95: SALDO
A96: 7 | B96: =B88 -> 46160 | C96: ='LIBRO DIARIO'!H38 -> VENTA DE 2 GENERADORES A GS. 20.000.000 C/U SEGÚN FACTURA | E96: ='LIBRO DIARIO'!J37 -> 4000000 | F96: =E96 -> 4000000
F98: =F96 -> 4000000
D99: 0 | E99: =E96 -> 4000000
A102: FOLIO: | B102: 13 | C102: CUENTA: | D102: COSTO DE MERCADERIAS
A103: NRO | B103: FECHA | C103: DESCRIPCIÓN | D103: DEBE | E103: HABER | F103: SALDO
A104: 8 | B104: =B96 -> 46160 | C104: ='LIBRO DIARIO'!H42 -> COSTEO SEGÚN INFORME DEPOSITO | D104: ='LIBRO DIARIO'!I40 -> 20000000 | F104: =D104 -> 20000000
F106: =F104 -> 20000000
D107: =D104 -> 20000000 | E107: 0
A110: FOLIO: | B110: 14 | C110: CUENTA: | D110: SUELDOS Y JORNALES
A111: NRO | B111: FECHA | C111: DESCRIPCIÓN | D111: DEBE | E111: HABER | F111: SALDO
A112: ='LIBRO DIARIO'!F44 -> 9 | B112: ='LIBRO DIARIO'!G44 -> 46173 | C112: ='LIBRO DIARIO'!H48 -> PAGO DE SALARIO AL PERSONAL | D112: ='LIBRO DIARIO'!I44 -> 5000000 | F112: =D112 -> 5000000
F114: =F112 -> 5000000
D115: =D112 -> 5000000 | E115: 0
A118: FOLIO: | B118: 15 | C118: CUENTA: | D118: APORTE PATRONAL
A119: NRO | B119: FECHA | C119: DESCRIPCIÓN | D119: DEBE | E119: HABER | F119: SALDO
A120: 9 | B120: ='LIBRO DIARIO'!G44 -> 46173 | C120: ='LIBRO DIARIO'!H48 -> PAGO DE SALARIO AL PERSONAL | D120: ='LIBRO DIARIO'!I45 -> 825000 | F120: =D120 -> 825000
F122: =F120 -> 825000
D123: =D120 -> 825000 | E123: 0
A126: FOLIO: | B126: 16 | C126: CUENTA: | D126: IPS A PAGAR
A127: NRO | B127: FECHA | C127: DESCRIPCIÓN | D127: DEBE | E127: HABER | F127: SALDO
A128: =A120 -> 9 | B128: =B120 -> 46173 | C128: ='LIBRO DIARIO'!H48 -> PAGO DE SALARIO AL PERSONAL | E128: ='LIBRO DIARIO'!J46 -> 1275000 | F128: =E128 -> 1275000
F130: =F128 -> 1275000
D131: 0 | E131: =E128 -> 1275000
A134: FOLIO: | B134: 17 | C134: CUENTA: | D134: HONORARIOS PROFESIONALES
A135: NRO | B135: FECHA | C135: DESCRIPCIÓN | D135: DEBE | E135: HABER | F135: SALDO
A136: ='LIBRO DIARIO'!F50 -> 10 | B136: ='LIBRO DIARIO'!G50 -> 46173 | C136: ='LIBRO DIARIO'!H53 -> PAGO DE HONROARIOS AL ABOGADO DE LA EMPRESA SEGÚN FACTURA | D136: ='LIBRO DIARIO'!I50 -> 6000000 | F136: =D136 -> 6000000
F138: =F136 -> 6000000
D139: =D136 -> 6000000 | E139: 0
A142: FOLIO: | B142: 18 | C142: CUENTA: | D142: HONORARIOS A PAGAR
A143: NRO | B143: FECHA | C143: DESCRIPCIÓN | D143: DEBE | E143: HABER | F143: SALDO
A144: =A136 -> 10 | B144: =B136 -> 46173 | C144: ='LIBRO DIARIO'!H53 -> PAGO DE HONROARIOS AL ABOGADO DE LA EMPRESA SEGÚN FACTURA | E144: ='LIBRO DIARIO'!J52 -> 6600000

Sheet BG _ER
A1: BALANCE DE COMPROBACIÓN DE SUMAS Y SALDOS - BALANCE GENERAL & ESTADO DE RESULTADOS
A3: Nro. | B3: CUENTA CONTABLE | C3: SUMAS | E3: SALDOS | G3: BALANCE GENERAL | I3: ESTADO DE RESULTADOS
C4: DEBE | D4: HABER | E4: DEUDOR | F4: ACREEDOR | G4: ACTIVO | H4: PASIVO/PN | I4: RES. NEGATIVO | J4: RES. POSITIVO
A5: 1 | B5: CAJA | C5: ='LIBRO MAYOR'!D7 -> 100000000 | D5: ='LIBRO MAYOR'!E7 -> 95000000 | E5: ='LIBRO MAYOR'!F6 -> 5000000 | G5: =E5 -> 5000000
A6: 2 | B6: CAPITAL | D6: ='LIBRO MAYOR'!E16 -> 100000000 | F6: =D6 -> 100000000 | H6: =F6 -> 100000000
A7: 3 | B7: ='LIBRO MAYOR'!D19 -> BANCO X CTA CTE | C7: ='LIBRO MAYOR'!D28 -> 139000000 | D7: ='LIBRO MAYOR'!E28 -> 29250000 | E7: ='LIBRO MAYOR'!F27 -> 109750000 | G7: =E7 -> 109750000
A8: 4 | B8: ='LIBRO MAYOR'!D30 -> IMPUESTOS, TASAS Y PATENTES | C8: ='LIBRO MAYOR'!D35 -> 600000 | E8: =C8 -> 600000 | I8: =E8 -> 600000
A9: 5 | B9: MERCADERIAS | C9: ='LIBRO MAYOR'!D44 -> 30000000 | D9: ='LIBRO MAYOR'!E44 -> 20000000 | E9: ='LIBRO MAYOR'!F43 -> 10000000 | G9: =E9 -> 10000000
A10: 6 | B10: ='LIBRO MAYOR'!D46 -> IVA CF 10% | C10: ='LIBRO MAYOR'!D52 -> 3820000 | E10: =C10 -> 3820000 | G10: =E10 -> 3820000
A11: 7 | B11: ='LIBRO MAYOR'!D54 -> PROVEEDORES | C11: ='LIBRO MAYOR'!D59 -> 3000000 | D11: ='LIBRO MAYOR'!E59 -> 13000000 | F11: ='LIBRO MAYOR'!F57 -> 16000000 | H11: =F11 -> 16000000
A12: 8 | B12: ='LIBRO MAYOR'!D62 -> MUEBLES Y EQUIPOS | C12: ='LIBRO MAYOR'!D67 -> 1200000 | E12: =C12 -> 1200000 | G12: =E12 -> 1200000
A13: 9 | B13: ='LIBRO MAYOR'!D70 -> ACREEDORES VARIOS | D13: ='LIBRO MAYOR'!E75 -> 1320000 | F13: =D13 -> 1320000 | H13: =F13 -> 1320000
A14: 10 | B14: ='LIBRO MAYOR'!D78 -> EQUIPOS DE INFORMATICA | C14: ='LIBRO MAYOR'!D83 -> 1000000 | E14: =C14 -> 1000000 | G14: =E14 -> 1000000
A15: 11 | B15: ='LIBRO MAYOR'!D86 -> VENTA DE MERCADERIAS | D15: ='LIBRO MAYOR'!E88 -> 40000000 | F15: =D15 -> 40000000 | J15: =F15 -> 40000000
A16: 12 | B16: ='LIBRO MAYOR'!D94 -> IVA DF 10% | D16: ='LIBRO MAYOR'!E99 -> 4000000 | F16: =D16 -> 4000000 | H16: =F16 -> 4000000
A17: 13 | B17: ='LIBRO MAYOR'!D102 -> COSTO DE MERCADERIAS | C17: ='LIBRO MAYOR'!D104 -> 20000000 | E17: =C17 -> 20000000 | I17: =E17 -> 20000000
A18: 14 | B18: ='LIBRO MAYOR'!D110 -> SUELDOS Y JORNALES | C18: ='LIBRO MAYOR'!D115 -> 5000000 | E18: =C18 -> 5000000 | I18: =E18 -> 5000000
A19: 15 | B19: ='LIBRO MAYOR'!D118 -> APORTE PATRONAL | C19: ='LIBRO MAYOR'!D120 -> 825000 | E19: =C19 -> 825000 | I19: =E19 -> 825000
A20: 16 | B20: ='LIBRO MAYOR'!D126 -> IPS A PAGAR | D20: ='LIBRO MAYOR'!E131 -> 1275000 | F20: =D20 -> 1275000 | H20: =F20 -> 1275000
A21: 17 | B21: HONORARIOS PROFESIONALES | C21: ='LIBRO MAYOR'!D139 -> 6000000 | E21: =C21 -> 6000000 | I21: =E21 -> 6000000
A22: 18 | B22: ='LIBRO MAYOR'!D142 -> HONORARIOS A PAGAR | D22: ='LIBRO MAYOR'!E144 -> 6600000 | F22: =D22 -> 6600000 | I22: =F22 -> 6600000
C23: =SUM(C5:C22) -> 310445000 | D23: =SUM(D5:D22) -> 310445000 | E23: =SUM(E5:E22) -> 163195000 | F23: =SUM(F5:F22) -> 169195000 | G23: =SUM(G5:G22) -> 130770000 | H23: =SUM(H5:H22) -> 122595000 | I23: =SUM(I5:I22) -> 39025000 | J23: =SUM(J5:J22) -> 40000000
H24: =G23-H23 -> 8175000 | I24: =J23-I23 -> 975000
H25: =SUM(H23:H24) -> 130770000 | I25: =SUM(I23:I24) -> 40000000
