Workbook

Sheet LIBRO DIARIO
B1: LIBRO DIARIO
B3: Cálculo Auxiliar en Esquema T | G3: FORMATO DEL LIBRO DIARIO
B4: DEBE | D4: HABER | G4: NRO | H4: FECHA | I4: CUENTAS CONTABLES | J4: DEBE | K4: HABER | P4: BG:Balance General
B5: FONDO FIJO | C5: 2500000 | D5: DEUDAS BANCARIAS | E5: 200000000 | G5: 1 | H5: 45413 | I5: FONDO FIJO | J5: =C5 -> 2500000 | P5: ER:Estado de Resultado
B6: BANCO GNB CTA CTE | C6: 450000000 | D6: INTERES A PAGAR | E6: =E5*180*12.5/36500 -> 12328767 | I6: BANCO GNB CTA CTE | J6: =C6 -> 450000000
B7: BANCO ITAU PLAZO FIJO | C7: 100000000 | D7: PASIVO | E7: =E5 -> 200000000
B8: DOCUMENTOS A COBRAR | C8: 1300000 | D8: CAPITAL | E8: =C10-E7 -> 353800000 | I8: BANCO ITAU PLAZO FIJO | J8: =C7 -> 100000000
I9: DOCUMENTOS A COBRAR | J9: =C8 -> 1300000
C10: =SUM(C5:C8) -> 553800000 | E10: =SUM(E7:E8) -> 553800000 | I10: DEUDAS BANCARIAS | K10: =E5 -> 200000000
A11: COMPRA | I11: CAPITAL | K11: =E8 -> 353800000
B12: MUEBLES Y UTILES | C12: =2650000/1.1 -> 2409090.9 | D12: BANCO GNB CTA CTE | E12: 2650000 | I12: ASIENTO DE APERTURA DE EMPRESA POLITEC
B13: IVA CF 10% | C13: =2650000/11 -> 240909.09
C14: =SUM(C12:C13) -> 2650000 | E14: =SUM(E12:E13) -> 2650000 | G14: 2 | H14: 45414 | I14: =B12 -> MUEBLES Y UTILES | J14: =C12 -> 2409090.9
I15: =B13 -> IVA CF 10% | J15: =C13 -> 240909.09
A16: COMPRA | I16: =D12 -> BANCO GNB CTA CTE | K16: =E12 -> 2650000
B17: MEDIOS DE TRANSPORTE | C17: =47000000/1.1 -> 42727273 | D17: BANCO GNB CTA CTE | E17: =47000000/2 -> 23500000 | I17: COMPRA DE MOBILIARIOS PARA USO DE LA EMPRESA
B18: IVA CF 10% | C18: =47000000/11 -> 4272727.3 | D18: ACREEDORES VARIOS | E18: =E17 -> 23500000
C19: =SUM(C17:C18) -> 47000000 | E19: =SUM(E17:E18) -> 47000000 | G19: 3 | H19: 45415 | I19: =B17 -> MEDIOS DE TRANSPORTE | J19: =C17 -> 42727273
I20: =B18 -> IVA CF 10% | J20: =C18 -> 4272727.3
A21: COMPRA | I21: =D17 -> BANCO GNB CTA CTE | K21: =E17 -> 23500000
A22: 5900000 | B22: MERCADERIAS | C22: =A22*35/1.1 -> 1.8772727e+08 | D22: BANCO GNB CTA CTE | E22: =35*A22 -> 206500000 | I22: =D18 -> ACREEDORES VARIOS | K22: =E18 -> 23500000
B23: IVA CF 10% | C23: =A22*35/11 -> 18772727 | D23: =D22 -> BANCO GNB CTA CTE | E23: =A24*30 -> 18000000 | I23: COMPRA DE CAMIONETA NISSAN SEGÚN FACTURA NRO.003-002-0016559
A24: 600000 | B24: MERCADERIAS | C24: =30*A24/1.1 -> 16363636
B25: IVA CF 10% | C25: =A24*30/11 -> 1636363.6 | G25: 4 | H25: 45416 | I25: =B22 -> MERCADERIAS | J25: =C22 -> 1.8772727e+08
C26: =SUM(C22:C25) -> 224500000 | E26: =SUM(E22:E25) -> 224500000 | F26: * | I26: =B23 -> IVA CF 10% | J26: =C23 -> 18772727
I27: =B24 -> MERCADERIAS | J27: =C24 -> 16363636
A28: VENTA | I28: =B25 -> IVA CF 10% | J28: =C25 -> 1636363.6
A29: 6800000 | B29: BANCO GNB CTA CTE | C29: =(A29*A30+A31*A32)*0.4 -> 103120000 | D29: VENTA DE MERCADERIAS | E29: =A29*A30/1.1 -> 2.1636364e+08 | I29: =D22 -> BANCO GNB CTA CTE | K29: =E22 -> 206500000
A30: 35 | B30: DOCUMENTOS A COBRAR | C30: =(A29*A30+A31*A32)*0.6 -> 154680000 | D30: IVA DF 10% | E30: =A29*A30/11 -> 21636364 | I30: =D23 -> BANCO GNB CTA CTE | K30: =E23 -> 18000000
A31: 900000 | D31: VENTA DE MERCADERIAS | E31: =A31*A32/1.1 -> 18000000 | I31: COMPRA DE MERCADERIAS
A32: 22 | D32: IVA DF 10% | E32: =A31*A32/11 -> 1800000
C33: =SUM(C29:C32) -> 257800000 | E33: =SUM(E29:E32) -> 2.578e+08 | G33: 5 | H33: 45418 | I33: =B29 -> BANCO GNB CTA CTE | J33: =C29 -> 103120000
I34: =B30 -> DOCUMENTOS A COBRAR | J34: =C30 -> 154680000
I35: =D29 -> VENTA DE MERCADERIAS | K35: =E29 -> 2.1636364e+08
A36: COSTO | I36: =D30 -> IVA DF 10% | K36: =E30 -> 21636364
A37: =A22/1.1 -> 5363636.4 | B37: COSTO DE VENTA | C37: =A30*A22/1.1 -> 1.8772727e+08 | D37: MERCADERIAS | E37: =C37 -> 1.8772727e+08 | I37: =D31 -> VENTA DE MERCADERIAS | K37: =E31 -> 18000000
A38: =A24/1.1 -> 545454.55 | B38: =B37 -> COSTO DE VENTA | C38: =A32*A38 -> 12000000 | D38: =D37 -> MERCADERIAS | E38: =C38 -> 12000000 | I38: =D32 -> IVA DF 10% | K38: =E33 -> 2.578e+08
C39: =SUM(C37:C38) -> 1.9972727e+08 | E39: =SUM(E37:E38) -> 1.9972727e+08 | I39: VENTA DE MERCADERIAS
G41: 6 | H41: =H33 -> 45418 | I41: =B37 -> COSTO DE VENTA | J41: =C37 -> 1.8772727e+08
A42: COMPRA | I42: =B38 -> COSTO DE VENTA | J42: =C38 -> 12000000
A43: 5900000 | B43: MERCADERIAS | C43: =A43*A44/1.1 -> 53636364 | D43: BANCO GNB CTA CTE | E43: =A43*A44 -> 59000000 | I43: =D37 -> MERCADERIAS | K43: =E37 -> 1.8772727e+08
A44: 10 | B44: IVA CF 10% | C44: =A43*A44/11 -> 5363636.4 | D44: =D43 -> BANCO GNB CTA CTE | E44: =A45*A46 -> 3000000 | I44: =D38 -> MERCADERIAS | K44: =E38 -> 12000000
A45: 600000 | B45: MERCADERIAS | C45: =A45*A46/1.1 -> 2727272.7 | I45: COSTEO DE VENTA
A46: 5 | B46: IVA CF 10% | C46: =A45*A46/11 -> 272727.27
C47: =SUM(C43:C46) -> 62000000 | E47: =SUM(E43:E46) -> 62000000 | G47: 7 | H47: 45420 | I47: =B43 -> MERCADERIAS | J47: =C43 -> 53636364
I48: =B44 -> IVA CF 10% | J48: =C44 -> 5363636.4
A49: VENTA | I49: =B45 -> MERCADERIAS | J49: =C45 -> 2727272.7
A50: 6800000 | B50: BANCO GNB CTA CTE | C50: =(A50*A51+A52*A53)*0.4 -> 36240000 | D50: VENTA DE MERCADERIAS | E50: =A50*A51/1.1 -> 74181818 | I50: =B46 -> IVA CF 10% | J50: =C46 -> 272727.27
A51: 12 | B51: DOCUMENTOS A COBRAR | C51: =(A50*A51+A52*A53)*0.6 -> 54360000 | D51: IVA DF 10% | E51: =A50*A51/11 -> 7418181.8 | I51: =D43 -> BANCO GNB CTA CTE | K51: =E43 -> 59000000
A52: 900000 | D52: VENTA DE MERCADERIAS | E52: =A52*A53/1.1 -> 8181818.2 | I52: =I51 -> BANCO GNB CTA CTE | K52: =E44 -> 3000000
A53: 10 | D53: IVA DF 10% | E53: =A52*A53/11 -> 818181.82 | I53: COMPRA DE MERCADERIAS A CONTADO
C54: =SUM(C50:C53) -> 90600000 | E54: =SUM(E50:E53) -> 90600000
G55: 8 | H55: 45418 | I55: =B50 -> BANCO GNB CTA CTE | J55: =C50 -> 36240000
I56: =B51 -> DOCUMENTOS A COBRAR | J56: =C51 -> 54360000
A57: COSTO | I57: =D50 -> VENTA DE MERCADERIAS | K57: =E50 -> 74181818
A58: =A43/1.1 -> 5363636.4 | B58: COSTO DE VENTA | C58: =A51*A43/1.1 -> 64363636 | D58: MERCADERIAS | E58: =C58 -> 64363636 | I58: =D51 -> IVA DF 10% | K58: =E51 -> 7418181.8
A59: =A45/1.1 -> 545454.55 | B59: =B58 -> COSTO DE VENTA | C59: =A53*A59 -> 5454545.5 | D59: =D58 -> MERCADERIAS | E59: =C59 -> 5454545.5 | I59: =D52 -> VENTA DE MERCADERIAS | K59: =E52 -> 8181818.2
C60: =SUM(C58:C59) -> 69818182 | E60: =SUM(E58:E59) -> 69818182 | I60: =D53 -> IVA DF 10% | K60: =E53 -> 818181.82
I61: VENTA DE MERCADERIAS
G63: 9 | H63: 45418 | I63: =B58 -> COSTO DE VENTA | J63: =C58 -> 64363636
B64: IMPUESTOS, TASAS Y PATENTES | C64: 500000 | D64: BANCO GNB CTA CTE | E64: =C64 -> 500000 | I64: =B59 -> COSTO DE VENTA | J64: =C59 -> 5454545.5
I65: =D58 -> MERCADERIAS | K65: =E58 -> 64363636
I66: =I65 -> MERCADERIAS | K66: =E59 -> 5454545.5
I67: COSTEO DE VENTA
G69: 10 | H69: 45421 | I69: =B64 -> IMPUESTOS, TASAS Y PATENTES | J69: =C64 -> 500000
A70: 1320000 | B70: MUEBLES Y UTILES | C70: =A70/1.1 -> 1200000 | D70: BANCO GNB CTA CTE | E70: =A70 -> 1320000 | I70: =D64 -> BANCO GNB CTA CTE | K70: =J69 -> 500000
B71: IVA CF 10% | C71: =A70/11 -> 120000 | I71: PAGO DE PATENTE COMERCIAL
G73: 11 | H73: 45424 | I73: =B70 -> MUEBLES Y UTILES | J73: =C70 -> 1200000
I74: =B71 -> IVA CF 10% | J74: =C71 -> 120000
I75: =D70 -> BANCO GNB CTA CTE | K75: =E70 -> 1320000
A76: 980000 | B76: LUZ, AGUA, TELEFONO A PAGAR | C76: =A76/1.1 -> 890909.09 | D76: BANCO GNB CTA CTE | E76: =A76 -> 980000 | I76: COMPRA DE PRODUCTOS DE LIMPIEZA
B77: IVA CF 10% | C77: =A76/11 -> 89090.909
G78: 12 | H78: 45427 | I78: =B76 -> LUZ, AGUA, TELEFONO A PAGAR | J78: =C76 -> 890909.09
I79: =B77 -> IVA CF 10% | J79: =C77 -> 89090.909
I80: =D76 -> BANCO GNB CTA CTE | K80: =E76 -> 980000
I81: PAGO DE SERVICIOS DE INTERNET
A82: 5080000 | B82: HONORARIOS PROFESIONALES | C82: =A82/1.1 -> 4618181.8 | D82: BANCO GNB CTA CTE | E82: =A82 -> 5080000
B83: IVA CF 10% | C83: =A82/11 -> 461818.18 | G83: 13 | H83: 45432 | I83: =B82 -> HONORARIOS PROFESIONALES | J83: =C82 -> 4618181.8
C84: =SUM(C82:C83) -> 5080000 | E84: =SUM(E82:E83) -> 5080000 | I84: =B83 -> IVA CF 10% | J84: =C83 -> 461818.18
I85: =D82 -> BANCO GNB CTA CTE | K85: =E82 -> 5080000
I86: PAGO DE HONORARIOS A CONTADOR
B87: DEBE | D87: HABER
B88: SUELDOS Y JORNALES | C88: 3000000 | D88: BANCO CTA CTE | E88: =C88*91% -> 2730000 | G88: 14 | H88: 45443 | I88: =B88 -> SUELDOS Y JORNALES | J88: =C88 -> 3000000
B89: APORTE PATRONAL | C89: =C88*16.5% -> 495000 | D89: IPS A PAGAR | E89: =C89+C88*9% -> 765000 | I89: =B89 -> APORTE PATRONAL | J89: =C89 -> 495000
C90: =SUM(C88:C89) -> 3495000 | E90: =SUM(E88:E89) -> 3495000 | I90: BANCO GNB CTA CTE | K90: =E88 -> 2730000
I91: =D89 -> IPS A PAGAR | K91: =E89 -> 765000
I92: SALARIO DE KARINA DUARTE
B93: DEBE | D93: HABER
B94: SUELDOS Y JORNALES | C94: 3500000 | D94: BANCO CTA CTE | E94: =C94*91% -> 3185000 | G94: 15 | H94: =H88 -> 45443 | I94: =B94 -> SUELDOS Y JORNALES | J94: =C94 -> 3500000
B95: APORTE PATRONAL | C95: =C94*16.5% -> 577500 | D95: IPS A PAGAR | E95: =C95+C94*9% -> 892500 | I95: =B95 -> APORTE PATRONAL | J95: =C95 -> 577500
C96: =SUM(C94:C95) -> 4077500 | E96: =SUM(E94:E95) -> 4077500 | I96: BANCO GNB CTA CTE | K96: =E94 -> 3185000
I97: =D95 -> IPS A PAGAR | K97: =E95 -> 892500
I98: SALARIO DE NELSON KANASAWA
B99: DEBE | D99: HABER
B100: SUELDOS Y JORNALES | C100: 2680373 | D100: BANCO CTA CTE | E100: =C100*91% -> 2439139.4 | G100: 16 | H100: =H94 -> 45443 | I100: =B100 -> SUELDOS Y JORNALES | J100: =C100 -> 2680373
B101: APORTE PATRONAL | C101: =C100*16.5% -> 442261.55 | D101: IPS A PAGAR | E101: =C101+C100*9% -> 683495.11 | I101: =B101 -> APORTE PATRONAL | J101: =C101 -> 442261.55
C102: =SUM(C100:C101) -> 3122634.5 | E102: =SUM(E100:E101) -> 3122634.5 | I102: BANCO GNB CTA CTE | K102: =E100 -> 2439139.4
I103: =D101 -> IPS A PAGAR | K103: =E101 -> 683495.11
I104: SALARIO DE JUAN FIGUEROA
J107: =SUM(J5:J106) -> 1.5264706e+09 | K107: =SUM(K5:K106) -> 1.7824706e+09

Sheet LIBRO MAYOR
A1: FORMATO DEL LIBRO MAYOR
A3: FOLIO: | B3: 1 | C3: CUENTA: | D3: ='LIBRO DIARIO'!I5 -> FONDO FIJO
A4: NRO | B4: FECHA | C4: DESCRIPCIÓN | D4: DEBE | E4: HABER | F4: SALDO
A5: ='LIBRO DIARIO'!G5 -> 1 | B5: ='LIBRO DIARIO'!H5 -> 45413 | C5: ='LIBRO DIARIO'!I12 -> ASIENTO DE APERTURA DE EMPRESA POLITEC | D5: ='LIBRO DIARIO'!J5 -> 2500000 | F5: =D5 -> 2500000
A11: FOLIO: | B11: 2 | C11: CUENTA: | D11: ='LIBRO DIARIO'!I6 -> BANCO GNB CTA CTE
A12: NRO | B12: FECHA | C12: DESCRIPCIÓN | D12: DEBE | E12: HABER | F12: SALDO
A13: ='LIBRO DIARIO'!G5 -> 1 | B13: =B5 -> 45413 | C13: =C5 -> ASIENTO DE APERTURA DE EMPRESA POLITEC | D13: ='LIBRO DIARIO'!J6 -> 450000000
A14: ='LIBRO DIARIO'!G14 -> 2 | B14: ='LIBRO DIARIO'!H14 -> 45414 | C14: ='LIBRO DIARIO'!I17 -> COMPRA DE MOBILIARIOS PARA USO DE LA EMPRESA | E14: ='LIBRO DIARIO'!K16 -> 2650000
A15: 3 | B15: ='LIBRO DIARIO'!H19 -> 45415 | C15: ='LIBRO DIARIO'!I23 -> COMPRA DE CAMIONETA NISSAN SEGÚN FACTURA NRO.003-002-0016559 | E15: ='LIBRO DIARIO'!K21 -> 23500000
A16: 4 | B16: ='LIBRO DIARIO'!H25 -> 45416 | C16: ='LIBRO DIARIO'!I31 -> COMPRA DE MERCADERIAS | E16: ='LIBRO DIARIO'!K29 -> 206500000
A17: 4 | B17: =B16 -> 45416 | C17: =C16 -> COMPRA DE MERCADERIAS | E17: ='LIBRO DIARIO'!K30 -> 18000000
A18: ='LIBRO DIARIO'!G33 -> 5 | B18: ='LIBRO DIARIO'!H33 -> 45418 | C18: ='LIBRO DIARIO'!I39 -> VENTA DE MERCADERIAS | D18: ='LIBRO DIARIO'!J33 -> 103120000
A19: 7 | B19: ='LIBRO DIARIO'!H47 -> 45420 | C19: ='LIBRO DIARIO'!I53 -> COMPRA DE MERCADERIAS A CONTADO | E19: ='LIBRO DIARIO'!K51 -> 59000000
A20: =A19 -> 7 | B20: =B19 -> 45420 | C20: =C19 -> COMPRA DE MERCADERIAS A CONTADO | E20: ='LIBRO DIARIO'!K52 -> 3000000
A21: 8 | B21: ='LIBRO DIARIO'!H55 -> 45418 | C21: ='LIBRO DIARIO'!I61 -> VENTA DE MERCADERIAS | E21: ='LIBRO DIARIO'!J55 -> 36240000
A22: 10 | B22: ='LIBRO DIARIO'!H69 -> 45421 | C22: ='LIBRO DIARIO'!I71 -> PAGO DE PATENTE COMERCIAL | E22: ='LIBRO DIARIO'!K70 -> 500000
A23: 11 | B23: 45424 | C23: ='LIBRO DIARIO'!I76 -> COMPRA DE PRODUCTOS DE LIMPIEZA | E23: ='LIBRO DIARIO'!K75 -> 1320000
A24: 12 | B24: ='LIBRO DIARIO'!H78 -> 45427 | C24: ='LIBRO DIARIO'!I81 -> PAGO DE SERVICIOS DE INTERNET | E24: ='LIBRO DIARIO'!K80 -> 980000
A25: ='LIBRO DIARIO'!G83 -> 13 | B25: ='LIBRO DIARIO'!H83 -> 45432 | C25: ='LIBRO DIARIO'!I86 -> PAGO DE HONORARIOS A CONTADOR | E25: ='LIBRO DIARIO'!K85 -> 5080000
A26: 14 | B26: ='LIBRO DIARIO'!H88 -> 45443 | C26: ='LIBRO DIARIO'!I92 -> SALARIO DE KARINA DUARTE | E26: ='LIBRO DIARIO'!K90 -> 2730000
A27: 15 | B27: =B26 -> 45443 | C27: ='LIBRO DIARIO'!I98 -> SALARIO DE NELSON KANASAWA | E27: ='LIBRO DIARIO'!K96 -> 3185000
A28: 16 | B28: =B26 -> 45443 | C28: ='LIBRO DIARIO'!I104 -> SALARIO DE JUAN FIGUEROA | E28: ='LIBRO DIARIO'!K97 -> 892500
A30: FOLIO: | B30: 3 | C30: CUENTA: | D30: BANCO ITAU PLAZO FIJO
A31: NRO | B31: FECHA | C31: DESCRIPCIÓN | D31: DEBE | E31: HABER | F31: SALDO
A32: 1 | B32: ='LIBRO DIARIO'!H5 -> 45413 | C32: ='LIBRO DIARIO'!I12 -> ASIENTO DE APERTURA DE EMPRESA POLITEC | D32: ='LIBRO DIARIO'!J8 -> 100000000
A38: FOLIO: | B38: 4 | C38: CUENTA: | D38: DOCUMENTOS A COBRAR
A39: NRO | B39: FECHA | C39: DESCRIPCIÓN | D39: DEBE | E39: HABER | F39: SALDO
A40: 1 | B40: =B32 -> 45413 | C40: =C32 -> ASIENTO DE APERTURA DE EMPRESA POLITEC | D40: ='LIBRO DIARIO'!J9 -> 1300000
A46: FOLIO: | B46: 5 | C46: CUENTA: | D46: ='LIBRO DIARIO'!I10 -> DEUDAS BANCARIAS
A47: NRO | B47: FECHA | C47: DESCRIPCIÓN | D47: DEBE | E47: HABER | F47: SALDO
A48: =A40 -> 1 | B48: =B40 -> 45413 | C48: =C40 -> ASIENTO DE APERTURA DE EMPRESA POLITEC | E48: ='LIBRO DIARIO'!K10 -> 200000000
A54: FOLIO: | B54: 6 | C54: CUENTA: | D54: ='LIBRO DIARIO'!I11 -> CAPITAL
A55: NRO | B55: FECHA | C55: DESCRIPCIÓN | D55: DEBE | E55: HABER | F55: SALDO
A56: 1 | B56: ='LIBRO DIARIO'!H5 -> 45413 | C56: =C48 -> ASIENTO DE APERTURA DE EMPRESA POLITEC | E56: =E48 -> 200000000
A62: FOLIO: | B62: 7 | C62: CUENTA: | D62: ='LIBRO DIARIO'!I14 -> MUEBLES Y UTILES
A63: NRO | B63: FECHA | C63: DESCRIPCIÓN | D63: DEBE | E63: HABER | F63: SALDO
A64: ='LIBRO DIARIO'!G14 -> 2 | B64: ='LIBRO DIARIO'!H14 -> 45414 | C64: ='LIBRO DIARIO'!I17 -> COMPRA DE MOBILIARIOS PARA USO DE LA EMPRESA | D64: ='LIBRO DIARIO'!J14 -> 2409090.9
A70: FOLIO: | B70: 7 | C70: CUENTA: | D70: ='LIBRO DIARIO'!I15 -> IVA CF 10%
A71: NRO | B71: FECHA | C71: DESCRIPCIÓN | D71: DEBE | E71: HABER | F71: SALDO
A72: ='LIBRO DIARIO'!G14 -> 2 | B72: ='LIBRO DIARIO'!H14 -> 45414 | C72: ='LIBRO DIARIO'!I17 -> COMPRA DE MOBILIARIOS PARA USO DE LA EMPRESA | D72: ='LIBRO DIARIO'!J15 -> 240909.09
A73: 3 | B73: ='LIBRO DIARIO'!H19 -> 45415 | C73: ='LIBRO DIARIO'!I23 -> COMPRA DE CAMIONETA NISSAN SEGÚN FACTURA NRO.003-002-0016559 | D73: ='LIBRO DIARIO'!J20 -> 4272727.3
A74: 4 | B74: ='LIBRO DIARIO'!H25 -> 45416 | C74: ='LIBRO DIARIO'!I31 -> COMPRA DE MERCADERIAS | D74: ='LIBRO DIARIO'!J26 -> 18772727
A75: =A74 -> 4 | B75: =B74 -> 45416 | C75: =C74 -> COMPRA DE MERCADERIAS | D75: ='LIBRO DIARIO'!J28 -> 1636363.6
A76: 7 | B76: ='LIBRO DIARIO'!H47 -> 45420 | C76: ='LIBRO DIARIO'!I53 -> COMPRA DE MERCADERIAS A CONTADO | D76: ='LIBRO DIARIO'!J48 -> 5363636.4
A77: =A76 -> 7 | B77: =B76 -> 45420 | C77: =C76 -> COMPRA DE MERCADERIAS A CONTADO | D77: ='LIBRO DIARIO'!J50 -> 272727.27
A81: FOLIO: | B81: 8 | C81: CUENTA:
A82: NRO | B82: FECHA | C82: DESCRIPCIÓN | D82: DEBE | E82: HABER | F82: SALDO
A89: FOLIO: | B89: 9 | C89: CUENTA:
A90: NRO | B90: FECHA | C90: DESCRIPCIÓN | D90: DEBE | E90: HABER | F90: SALDO
A97: FOLIO: | B97: 10 | C97: CUENTA:
A98: NRO | B98: FECHA | C98: DESCRIPCIÓN | D98: DEBE | E98: HABER | F98: SALDO
A105: FOLIO: | C105: CUENTA:
A106: NRO | B106: FECHA | C106: DESCRIPCIÓN | D106: DEBE | E106: HABER | F106: SALDO
A113: FOLIO: | C113: CUENTA:
A114: NRO | B114: FECHA | C114: DESCRIPCIÓN | D114: DEBE | E114: HABER | F114: SALDO

Sheet BG _ER
A1: BALANCE DE COMPROBACIÓN DE SUMAS Y SALDOS - BALANCE GENERAL & ESTADO DE RESULTADOS
A3: Nro. | B3: CUENTA CONTABLE | C3: SUMAS | E3: SALDOS | G3: BALANCE GENERAL | I3: ESTADO DE RESULTADOS
C4: DEBE | D4: HABER | E4: DEUDOR | F4: ACREEDOR | G4: ACTIVO | H4: PASIVO/PN | I4: RES. NEGATIVO | J4: RES. POSITIVO
A5: ='LIBRO MAYOR'!B3 -> 1 | B5: ='LIBRO MAYOR'!D3 -> FONDO FIJO
A6: ='LIBRO MAYOR'!B11 -> 2 | B6: ='LIBRO MAYOR'!D11 -> BANCO GNB CTA CTE
A7: ='LIBRO MAYOR'!B30 -> 3 | B7: ='LIBRO MAYOR'!D30 -> BANCO ITAU PLAZO FIJO
